megolm_filter.py
megolm_filter-0.2.dist-info/METADATA
megolm_filter-0.2.dist-info/WHEEL
megolm_filter-0.2.dist-info/entry_points.txt
megolm_filter-0.2.dist-info/licenses/LICENSE
megolm_filter-0.2.dist-info/RECORD
