Metadata-Version: 2.4
Name: megolm-filter
Version: 0.2
Summary: Modify your offline megolm key backups from shell
Project-URL: homepage, https://git.serialexperiments.club/lain/megolm_filter
Project-URL: repository, https://git.serialexperiments.club
Project-URL: changelog, https://git.serialexperiments.club/lain/megolm_filter/commits/branch/master
Author-email: Lain Iwakura <lain@serialexperiments.club>
License: GPLv3
License-File: LICENSE
Keywords: element,matrix,megolm
Classifier: Development Status :: 5 - Production/Stable
Classifier: Environment :: Console
Classifier: License :: OSI Approved :: GNU General Public License v3 (GPLv3)
Classifier: Operating System :: OS Independent
Classifier: Programming Language :: Python :: 3
Classifier: Topic :: Security :: Cryptography
Requires-Python: >=3.6
Requires-Dist: pycryptodome
